timeprintformat/__init__.py
timeprintformat-1.0.0.dist-info/LICENSE
timeprintformat-1.0.0.dist-info/METADATA
timeprintformat-1.0.0.dist-info/WHEEL
timeprintformat-1.0.0.dist-info/top_level.txt
timeprintformat-1.0.0.dist-info/RECORD
